blessedviewer.py
blessedviewer-0.1.0.dist-info/LICENSE
blessedviewer-0.1.0.dist-info/METADATA
blessedviewer-0.1.0.dist-info/WHEEL
blessedviewer-0.1.0.dist-info/entry_points.txt
blessedviewer-0.1.0.dist-info/RECORD
