Metadata-Version: 2.3
Name: blessedviewer
Version: 0.1.0
Summary: A blessed terminal-based image viewer
Author: Ashkan Feyzollahi
Author-email: ashkanfeyzollahi@gmail.com
Requires-Python: >=3.13
Classifier: Programming Language :: Python :: 3
Classifier: Programming Language :: Python :: 3.13
Requires-Dist: blessed (>=1.21.0,<2.0.0)
Requires-Dist: click (>=8.2.1,<9.0.0)
Requires-Dist: numpy (>=2.3.3,<3.0.0)
Requires-Dist: pillow (>=11.3.0,<12.0.0)
